syn/example.sv
module rle_compressor (
    input  logic       clk,
    input  logic       rst_n,
    input  logic [7:0] data_in,
    input  logic       valid_in,
    output logic [7:0] data_out,
    output logic [7:0] count_out,
    output logic       valid_out
);

    logic [7:0] last_byte;
    logic [7:0] counter;

    always_ff @(posedge clk or negedge rst_n) begin
        if (!rst_n) begin
            counter   <= 8'd0;
            valid_out <= 1'b0;
            last_byte <= 8'd0;
        end else if (valid_in) begin
            if (data_in == last_byte && counter < 8'hFF) begin
                counter   <= counter + 1;
                valid_out <= 1'b0;
            end else begin
                data_out  <= last_byte;
                count_out <= counter;
                valid_out <= (counter > 0);

                last_byte <= data_in;
                counter   <= 8'd1;
            end
        end else begin
            valid_out <= 1'b0;
        end
    end
endmodule

sim/example_tb.sv
module example_tb;
    logic clk = 0;
    logic rst_n;
    logic [7:0] data_in;
    logic valid_in;
    logic [7:0] data_out;
    logic [7:0] count_out;
    logic valid_out;

    // Clock generation (100MHz)
    always #5 clk = ~clk;

    rle_compressor dut (.*);

    initial begin
        // Initialize
        rst_n = 0;
        valid_in = 0;
        data_in = 0;

        #20 rst_n = 1;

        // Feed data: AAAABBC
        send_byte(8'h41); // A
        send_byte(8'h41); // A
        send_byte(8'h41); // A
        send_byte(8'h41); // A
        send_byte(8'h42); // B
        send_byte(8'h42); // B
        send_byte(8'h43); // C
        send_byte(8'h00); // Flush last byte

        #50 $finish;
    end

    task send_byte(input [7:0] b);
        @(posedge clk);
        data_in = b;
        valid_in = 1;
        #1; // Small delay for waveform readability
    endtask

endmodule

sim/gen/vcd/example_tb_20260228_160917.vcd
$date
	Sat Feb 28 16:09:17 2026
$end
$version
	Icarus Verilog
$end
$timescale
	1s
$end
$scope module example_tb $end
$var wire 1 ! valid_out $end
$var wire 8 " data_out [7:0] $end
$var wire 8 # count_out [7:0] $end
$var reg 1 $ clk $end
$var reg 8 % data_in [7:0] $end
$var reg 1 & rst_n $end
$var reg 1 ' valid_in $end
$scope module dut $end
$var wire 1 $ clk $end
$var wire 8 ( data_in [7:0] $end
$var wire 1 & rst_n $end
$var wire 1 ' valid_in $end
$var reg 8 ) count_out [7:0] $end
$var reg 8 * counter [7:0] $end
$var reg 8 + data_out [7:0] $end
$var reg 8 , last_byte [7:0] $end
$var reg 1 ! valid_out $end
$upscope $end
$scope task send_byte $end
$var reg 8 - b [7:0] $end
$upscope $end
$upscope $end
$scope module dump_trigger $end
$upscope $end
$enddefinitions $end
$comment Show the parameter values. $end
$dumpall
$end
#0
$dumpvars
bx -
b0 ,
bx +
b0 *
bx )
b0 (
0'
0&
b0 %
0$
bx #
bx "
0!
$end
#5
1$
#10
0$
#15
1$
#20
0$
b1000001 -
1&
#25
b1 *
b1000001 ,
b0 #
b0 )
b0 "
b0 +
1'
b1000001 %
b1000001 (
1$
#30
0$
#35
b10 *
1$
#40
0$
#45
b11 *
1$
#50
0$
#55
b100 *
1$
#56
b1000010 -
#60
0$
#65
b1 *
b1000010 ,
1!
b100 #
b100 )
b1000001 "
b1000001 +
b1000010 %
b1000010 (
1$
#70
0$
#75
0!
b10 *
1$
#76
b1000011 -
#80
0$
#85
b1 *
b1000011 ,
1!
b10 #
b10 )
b1000010 "
b1000010 +
b1000011 %
b1000011 (
1$
#86
b0 -
#90
0$
#95
b0 ,
b1 #
b1 )
b1000011 "
b1000011 +
b0 %
b0 (
1$
#100
0$
#105
0!
b10 *
1$
#110
0$
#115
b11 *
1$
#120
0$
#125
b100 *
1$
#130
0$
#135
b101 *
1$
#140
0$
#145
b110 *
1$
